LICENSE.txt
README.md
setup.py
scorecard_generator/__init__.py
scorecard_generator/scorecard.py
scorecard_generator.egg-info/PKG-INFO
scorecard_generator.egg-info/SOURCES.txt
scorecard_generator.egg-info/dependency_links.txt
scorecard_generator.egg-info/requires.txt
scorecard_generator.egg-info/top_level.txt